qonduit/__init__.py
qonduit/_version.py
qonduit/_backend/__init__.py
qonduit/_backend/_cirq.py
qonduit/_backend/_default.py
qonduit/_backend/_pulsemaker.py
qonduit/_backend/_qiskit.py
qonduit/_backend/_quirk.py
qonduit/dashboard/Circuit.py
qonduit/dashboard/Default.py
qonduit/dashboard/Simple.py
qonduit/dashboard/__init__.py
qonduit/visualization/__init__.py
qonduit/visualization/circuit.py
qonduit/visualization/metrics.py
qonduit/visualization/pulse.py
qonduit/visualization/state.py
qonduit-0.1.2b2.dist-info/LICENSE
qonduit-0.1.2b2.dist-info/METADATA
qonduit-0.1.2b2.dist-info/WHEEL
qonduit-0.1.2b2.dist-info/top_level.txt
qonduit-0.1.2b2.dist-info/RECORD
